s1290242_learn/__init__.py
s1290242_learn/statistics/__init__.py
s1290242_learn/statistics/frequencyOfItems.py
s1290242_learn/visualization/__init__.py
s1290242_learn/visualization/heatMapItemsFrequency.py
s1290242_learn-2023.8.2.1.dist-info/LICENSE
s1290242_learn-2023.8.2.1.dist-info/METADATA
s1290242_learn-2023.8.2.1.dist-info/WHEEL
s1290242_learn-2023.8.2.1.dist-info/top_level.txt
s1290242_learn-2023.8.2.1.dist-info/RECORD
